{"item:ae2powertools:priority_tuner":[{"id":43561,"c":"minecraft.crafting","cn":"Crafting","ip":"data/locales/en_us/categories/minecraft.crafting/recipe_2608.png","o":[{"id":"item:ae2powertools:priority_tuner","name":"Priority Tuner"}],"in":[{"id":"item:minecraft:iron_ingot","qty":4,"name":"Iron Ingot"},{"id":"item:appliedenergistics2:material:1","qty":1,"name":"Charged Certus Quartz Crystal"},{"id":"item:appliedenergistics2:smooth_sky_stone_block","qty":1,"name":"Sky Stone Block"}]}],"item:ae2powertools:network_health_scanner":[{"id":43562,"c":"minecraft.crafting","cn":"Crafting","ip":"data/locales/en_us/categories/minecraft.crafting/recipe_2609.png","o":[{"id":"item:ae2powertools:network_health_scanner","name":"Network Health Scanner"}],"in":[{"id":"item:appliedenergistics2:smooth_sky_stone_block","qty":4,"name":"Sky Stone Block"},{"id":"item:appliedenergistics2:material:41","qty":1,"name":"Wireless Receiver"},{"id":"item:appliedenergistics2:material:23","qty":3,"name":"Calculation Processor"},{"id":"item:appliedenergistics2:part:200","qty":1,"name":"Dark Illuminated Panel"}]}],"item:ae2powertools:cards_distributor":[{"id":43563,"c":"minecraft.crafting","cn":"Crafting","ip":"data/locales/en_us/categories/minecraft.crafting/recipe_2610.png","o":[{"id":"item:ae2powertools:cards_distributor","name":"Cards Distributor"}],"in":[{"id":"item:appliedenergistics2:material:5","qty":4,"name":"Silicon"},{"id":"item:appliedenergistics2:material:41","qty":1,"name":"Wireless Receiver"},{"id":"item:appliedenergistics2:material:25","qty":1,"name":"Basic Card"},{"id":"item:appliedenergistics2:material:23","qty":1,"name":"Calculation Processor"},{"id":"item:appliedenergistics2:material:28","qty":1,"name":"Advanced Card"},{"id":"item:minecraft:iron_ingot","qty":1,"name":"Iron Ingot"}]}],"item:ae2powertools:better_level_maintainer":[{"id":52656,"c":"minecraft.crafting","cn":"Crafting","ip":"data/locales/en_us/categories/minecraft.crafting/recipe_28703.png","o":[{"id":"item:ae2powertools:better_level_maintainer","name":"Better Level Maintainer"}],"in":[{"id":"item:threng:material:0","qty":2,"name":"Fluix Steel Ingot"},{"id":"item:appliedenergistics2:part:160","qty":1,"name":"Bright Illuminated Panel"},{"id":"item:appliedenergistics2:material:9","qty":2,"name":"Fluix Pearl"},{"id":"item:appliedenergistics2:quartz_pillar","qty":1,"name":"Certus Quartz Pillar"},{"id":"item:appliedenergistics2:material:53","qty":2,"name":"Crafting Card"},{"id":"item:appliedenergistics2:material:38","qty":1,"name":"64k ME Storage Component"}]}],"item:ae2powertools:auto_crafter":[{"id":52673,"c":"minecraft.crafting","cn":"Crafting","ip":"data/locales/en_us/categories/minecraft.crafting/recipe_28720.png","o":[{"id":"item:ae2powertools:auto_crafter","qty":16,"name":"AE2 AutoCrafter"}],"in":[{"id":"item:appliedenergistics2:molecular_assembler","qty":2,"name":"Molecular Assembler"},{"id":"item:nae2:storage_crafting_16384k","qty":1,"name":"16MB Crafting Storage"},{"id":"item:nae2:coprocessor_64x","qty":2,"name":"64x Crafting Co-Processing Unit"},{"id":"item:ae2powertools:better_level_maintainer","qty":1,"name":"Better Level Maintainer"},{"id":"item:appliedenergistics2:material:12","qty":2,"name":"Pure Fluix Crystal"},{"id":"item:cells:singularity_processor:0","qty":1,"name":"Singularity Calculation Processor"}]}],"item:ae2powertools:crafter_speed_upgrade:0":[{"id":52675,"c":"minecraft.crafting","cn":"Crafting","ip":"data/locales/en_us/categories/minecraft.crafting/recipe_28722.png","o":[{"id":"item:ae2powertools:crafter_speed_upgrade:0","name":"Speed Upgrade I"}],"in":[{"id":"item:appliedenergistics2:molecular_assembler","qty":4,"name":"Molecular Assembler"},{"id":"item:appliedenergistics2:crafting_storage_64k","qty":2,"name":"64k Crafting Storage"},{"id":"item:appliedenergistics2:crafting_accelerator","qty":2,"name":"Crafting Co-Processing Unit"},{"id":"item:contenttweaker:multithreading_controller_upgrade","qty":1,"name":"Multithreading Component"}]}],"item:ae2powertools:crafter_speed_upgrade:1":[{"id":52676,"c":"minecraft.crafting","cn":"Crafting","ip":"data/locales/en_us/categories/minecraft.crafting/recipe_28723.png","o":[{"id":"item:ae2powertools:crafter_speed_upgrade:1","name":"Speed Upgrade II"}],"in":[{"id":"item:contenttweaker:promethium_shard","qty":4,"name":"Promethium Shard"},{"id":"item:ae2powertools:crafter_speed_upgrade:0","qty":4,"name":"Speed Upgrade I"},{"id":"item:contenttweaker:multithreading_controller_upgrade","qty":1,"name":"Multithreading Component"}]}]}