{"item:projectred-exploration:stone:3":[{"id":594,"c":"AlloySmelter","cn":"Alloysmelter","ip":"data/locales/en_us/categories/AlloySmelter/recipe_593.png","o":[{"id":"item:projectred-exploration:stone:3","name":"Basalt"}],"in":[{"id":"item:projectred-exploration:stone:2","qty":1,"name":"Basalt Cobblestone"},{"id":"crazypants.enderio.base.integration.jei.energy.energyingredient:enderio:energy","qty":1,"name":"2,000 µI"}]},{"id":24556,"c":"jeresources.worldgen","cn":"Worldgen","ip":"data/locales/en_us/categories/jeresources.worldgen/recipe_1215.png","o":[{"id":"item:projectred-exploration:stone:3","name":"Basalt"},{"id":"item:projectred-exploration:stone:2","name":"Basalt Cobblestone"}],"in":[]},{"id":62708,"c":"minecraft.smelting","cn":"Smelting","ip":"data/locales/en_us/categories/minecraft.smelting/recipe_294.png","o":[{"id":"item:projectred-exploration:stone:3","name":"Basalt"}],"in":[{"id":"item:projectred-exploration:stone:2","qty":1,"name":"Basalt Cobblestone"}]},{"id":66731,"c":"modularmachinery.recipes.mythic_processor_furnace","cn":"Mythic Processor Furnace","ip":"data/locales/en_us/categories/modularmachinery.recipes.mythic_processor_furnace/recipe_426.png","o":[{"id":"item:projectred-exploration:stone:3","qty":2,"name":"Basalt"}],"in":[{"id":"item:projectred-exploration:stone:2","qty":2,"name":"Basalt Cobblestone"}],"p":6},{"id":77411,"c":"thermalexpansion.furnace","cn":"Furnace","ip":"data/locales/en_us/categories/thermalexpansion.furnace/recipe_29.png","o":[{"id":"item:projectred-exploration:stone:3","name":"Basalt"}],"in":[{"id":"item:projectred-exploration:stone:2","qty":1,"name":"Basalt Cobblestone"}]}],"item:projectred-exploration:ore:6":[{"id":14331,"c":"environmentaltech.voidminer.ore.t1","cn":"T1","ip":"data/locales/en_us/categories/environmentaltech.voidminer.ore.t1/recipe_45.png","o":[{"id":"item:projectred-exploration:ore:6","name":"Electrotine Ore"}],"in":[{"id":"item:environmentaltech:laser_lens","qty":1,"name":"Clear Laser Lens"},{"id":"item:environmentaltech:laser_lens_colored:11","qty":1,"name":"Blue Laser Lens"}]},{"id":14406,"c":"environmentaltech.voidminer.ore.t2","cn":"T2","ip":"data/locales/en_us/categories/environmentaltech.voidminer.ore.t2/recipe_49.png","o":[{"id":"item:projectred-exploration:ore:6","name":"Electrotine Ore"}],"in":[{"id":"item:environmentaltech:laser_lens","qty":1,"name":"Clear Laser Lens"},{"id":"item:environmentaltech:laser_lens_colored:11","qty":1,"name":"Blue Laser Lens"}]},{"id":14479,"c":"environmentaltech.voidminer.ore.t3","cn":"T3","ip":"data/locales/en_us/categories/environmentaltech.voidminer.ore.t3/recipe_50.png","o":[{"id":"item:projectred-exploration:ore:6","name":"Electrotine Ore"}],"in":[{"id":"item:environmentaltech:laser_lens","qty":1,"name":"Clear Laser Lens"},{"id":"item:environmentaltech:laser_lens_colored:11","qty":1,"name":"Blue Laser Lens"}]},{"id":14553,"c":"environmentaltech.voidminer.ore.t4","cn":"T4","ip":"data/locales/en_us/categories/environmentaltech.voidminer.ore.t4/recipe_51.png","o":[{"id":"item:projectred-exploration:ore:6","name":"Electrotine Ore"}],"in":[{"id":"item:environmentaltech:laser_lens","qty":1,"name":"Clear Laser Lens"},{"id":"item:environmentaltech:laser_lens_colored:11","qty":1,"name":"Blue Laser Lens"}]},{"id":14629,"c":"environmentaltech.voidminer.ore.t5","cn":"T5","ip":"data/locales/en_us/categories/environmentaltech.voidminer.ore.t5/recipe_53.png","o":[{"id":"item:projectred-exploration:ore:6","name":"Electrotine Ore"}],"in":[{"id":"item:environmentaltech:laser_lens","qty":1,"name":"Clear Laser Lens"},{"id":"item:environmentaltech:laser_lens_colored:11","qty":1,"name":"Blue Laser Lens"}]},{"id":14710,"c":"environmentaltech.voidminer.ore.t6","cn":"T6","ip":"data/locales/en_us/categories/environmentaltech.voidminer.ore.t6/recipe_58.png","o":[{"id":"item:projectred-exploration:ore:6","name":"Electrotine Ore"}],"in":[{"id":"item:environmentaltech:laser_lens","qty":1,"name":"Clear Laser Lens"},{"id":"item:environmentaltech:laser_lens_colored:11","qty":1,"name":"Blue Laser Lens"}]},{"id":23443,"c":"jeresources.worldgen","cn":"Worldgen","ip":"data/locales/en_us/categories/jeresources.worldgen/recipe_102.png","o":[{"id":"item:projectred-exploration:ore:6","name":"Electrotine Ore"},{"id":"item:projectred-core:resource_item:105","qty":3,"name":"Electrotine"}],"in":[]},{"id":23906,"c":"jeresources.worldgen","cn":"Worldgen","ip":"data/locales/en_us/categories/jeresources.worldgen/recipe_565.png","o":[{"id":"item:projectred-exploration:ore:6","name":"Electrotine Ore"},{"id":"item:projectred-core:resource_item:105","qty":3,"name":"Electrotine"}],"in":[]},{"id":23925,"c":"jeresources.worldgen","cn":"Worldgen","ip":"data/locales/en_us/categories/jeresources.worldgen/recipe_584.png","o":[{"id":"item:projectred-exploration:ore:6","name":"Electrotine Ore"},{"id":"item:projectred-core:resource_item:105","qty":3,"name":"Electrotine"}],"in":[]},{"id":23952,"c":"jeresources.worldgen","cn":"Worldgen","ip":"data/locales/en_us/categories/jeresources.worldgen/recipe_611.png","o":[{"id":"item:projectred-exploration:ore:6","name":"Electrotine Ore"},{"id":"item:projectred-core:resource_item:105","qty":3,"name":"Electrotine"}],"in":[]},{"id":24360,"c":"jeresources.worldgen","cn":"Worldgen","ip":"data/locales/en_us/categories/jeresources.worldgen/recipe_1019.png","o":[{"id":"item:projectred-exploration:ore:6","name":"Electrotine Ore"},{"id":"item:projectred-core:resource_item:105","qty":3,"name":"Electrotine"}],"in":[]},{"id":24814,"c":"jeresources.worldgen","cn":"Worldgen","ip":"data/locales/en_us/categories/jeresources.worldgen/recipe_1473.png","o":[{"id":"item:projectred-exploration:ore:6","name":"Electrotine Ore"},{"id":"item:projectred-core:resource_item:105","qty":3,"name":"Electrotine"}],"in":[]},{"id":24828,"c":"jeresources.worldgen","cn":"Worldgen","ip":"data/locales/en_us/categories/jeresources.worldgen/recipe_1487.png","o":[{"id":"item:projectred-exploration:ore:6","name":"Electrotine Ore"},{"id":"item:projectred-core:resource_item:105","qty":3,"name":"Electrotine"}],"in":[]},{"id":24988,"c":"jeresources.worldgen","cn":"Worldgen","ip":"data/locales/en_us/categories/jeresources.worldgen/recipe_1647.png","o":[{"id":"item:projectred-exploration:ore:6","name":"Electrotine Ore"},{"id":"item:projectred-core:resource_item:105","qty":3,"name":"Electrotine"}],"in":[]},{"id":25236,"c":"jeresources.worldgen","cn":"Worldgen","ip":"data/locales/en_us/categories/jeresources.worldgen/recipe_1895.png","o":[{"id":"item:projectred-exploration:ore:6","name":"Electrotine Ore"},{"id":"item:projectred-core:resource_item:105","qty":3,"name":"Electrotine"}],"in":[]},{"id":25818,"c":"jeresources.worldgen","cn":"Worldgen","ip":"data/locales/en_us/categories/jeresources.worldgen/recipe_2477.png","o":[{"id":"item:projectred-exploration:ore:6","name":"Electrotine Ore"},{"id":"item:projectred-core:resource_item:105","qty":3,"name":"Electrotine"}],"in":[]},{"id":25822,"c":"jeresources.worldgen","cn":"Worldgen","ip":"data/locales/en_us/categories/jeresources.worldgen/recipe_2481.png","o":[{"id":"item:projectred-exploration:ore:6","name":"Electrotine Ore"},{"id":"item:projectred-core:resource_item:105","qty":3,"name":"Electrotine"}],"in":[]},{"id":26152,"c":"jeresources.worldgen","cn":"Worldgen","ip":"data/locales/en_us/categories/jeresources.worldgen/recipe_2811.png","o":[{"id":"item:projectred-exploration:ore:6","name":"Electrotine Ore"},{"id":"item:projectred-core:resource_item:105","qty":3,"name":"Electrotine"}],"in":[]},{"id":26343,"c":"jeresources.worldgen","cn":"Worldgen","ip":"data/locales/en_us/categories/jeresources.worldgen/recipe_3002.png","o":[{"id":"item:projectred-exploration:ore:6","name":"Electrotine Ore"},{"id":"item:projectred-core:resource_item:105","qty":3,"name":"Electrotine"}],"in":[]},{"id":26377,"c":"jeresources.worldgen","cn":"Worldgen","ip":"data/locales/en_us/categories/jeresources.worldgen/recipe_3036.png","o":[{"id":"item:projectred-exploration:ore:6","name":"Electrotine Ore"},{"id":"item:projectred-core:resource_item:105","qty":3,"name":"Electrotine"}],"in":[]},{"id":27305,"c":"jeresources.worldgen","cn":"Worldgen","ip":"data/locales/en_us/categories/jeresources.worldgen/recipe_3964.png","o":[{"id":"item:projectred-exploration:ore:6","name":"Electrotine Ore"},{"id":"item:projectred-core:resource_item:105","qty":3,"name":"Electrotine"}],"in":[]},{"id":27733,"c":"jeresources.worldgen","cn":"Worldgen","ip":"data/locales/en_us/categories/jeresources.worldgen/recipe_4392.png","o":[{"id":"item:projectred-exploration:ore:6","name":"Electrotine Ore"},{"id":"item:projectred-core:resource_item:105","qty":3,"name":"Electrotine"}],"in":[]},{"id":29252,"c":"jeresources.worldgen","cn":"Worldgen","ip":"data/locales/en_us/categories/jeresources.worldgen/recipe_5911.png","o":[{"id":"item:projectred-exploration:ore:6","name":"Electrotine Ore"},{"id":"item:projectred-core:resource_item:105","qty":3,"name":"Electrotine"}],"in":[]},{"id":29527,"c":"jeresources.worldgen","cn":"Worldgen","ip":"data/locales/en_us/categories/jeresources.worldgen/recipe_6186.png","o":[{"id":"item:projectred-exploration:ore:6","name":"Electrotine Ore"},{"id":"item:projectred-core:resource_item:105","qty":3,"name":"Electrotine"}],"in":[]},{"id":29568,"c":"jeresources.worldgen","cn":"Worldgen","ip":"data/locales/en_us/categories/jeresources.worldgen/recipe_6227.png","o":[{"id":"item:projectred-exploration:ore:6","name":"Electrotine Ore"},{"id":"item:projectred-core:resource_item:105","qty":3,"name":"Electrotine"}],"in":[]},{"id":29735,"c":"jeresources.worldgen","cn":"Worldgen","ip":"data/locales/en_us/categories/jeresources.worldgen/recipe_6394.png","o":[{"id":"item:projectred-exploration:ore:6","name":"Electrotine Ore"},{"id":"item:projectred-core:resource_item:105","qty":3,"name":"Electrotine"}],"in":[]}],"item:projectred-exploration:stone:0":[{"id":14772,"c":"environmentaltech.voidminer.resource.t1","cn":"T1","ip":"data/locales/en_us/categories/environmentaltech.voidminer.resource.t1/recipe_39.png","o":[{"id":"item:projectred-exploration:stone:0","name":"Marble"}],"in":[{"id":"item:environmentaltech:laser_lens","qty":1,"name":"Clear Laser Lens"},{"id":"item:environmentaltech:laser_lens_colored:0","qty":1,"name":"White Laser Lens"}]},{"id":14826,"c":"environmentaltech.voidminer.resource.t2","cn":"T2","ip":"data/locales/en_us/categories/environmentaltech.voidminer.resource.t2/recipe_39.png","o":[{"id":"item:projectred-exploration:stone:0","name":"Marble"}],"in":[{"id":"item:environmentaltech:laser_lens","qty":1,"name":"Clear Laser Lens"},{"id":"item:environmentaltech:laser_lens_colored:0","qty":1,"name":"White Laser Lens"}]},{"id":14880,"c":"environmentaltech.voidminer.resource.t3","cn":"T3","ip":"data/locales/en_us/categories/environmentaltech.voidminer.resource.t3/recipe_39.png","o":[{"id":"item:projectred-exploration:stone:0","name":"Marble"}],"in":[{"id":"item:environmentaltech:laser_lens","qty":1,"name":"Clear Laser Lens"},{"id":"item:environmentaltech:laser_lens_colored:0","qty":1,"name":"White Laser Lens"}]},{"id":14934,"c":"environmentaltech.voidminer.resource.t4","cn":"T4","ip":"data/locales/en_us/categories/environmentaltech.voidminer.resource.t4/recipe_39.png","o":[{"id":"item:projectred-exploration:stone:0","name":"Marble"}],"in":[{"id":"item:environmentaltech:laser_lens","qty":1,"name":"Clear Laser Lens"},{"id":"item:environmentaltech:laser_lens_colored:0","qty":1,"name":"White Laser Lens"}]},{"id":14990,"c":"environmentaltech.voidminer.resource.t5","cn":"T5","ip":"data/locales/en_us/categories/environmentaltech.voidminer.resource.t5/recipe_39.png","o":[{"id":"item:projectred-exploration:stone:0","name":"Marble"}],"in":[{"id":"item:environmentaltech:laser_lens","qty":1,"name":"Clear Laser Lens"},{"id":"item:environmentaltech:laser_lens_colored:0","qty":1,"name":"White Laser Lens"}]},{"id":15046,"c":"environmentaltech.voidminer.resource.t6","cn":"T6","ip":"data/locales/en_us/categories/environmentaltech.voidminer.resource.t6/recipe_39.png","o":[{"id":"item:projectred-exploration:stone:0","name":"Marble"}],"in":[{"id":"item:environmentaltech:laser_lens","qty":1,"name":"Clear Laser Lens"},{"id":"item:environmentaltech:laser_lens_colored:0","qty":1,"name":"White Laser Lens"}]},{"id":24412,"c":"jeresources.worldgen","cn":"Worldgen","ip":"data/locales/en_us/categories/jeresources.worldgen/recipe_1071.png","o":[{"id":"item:projectred-exploration:stone:0","name":"Marble"}],"in":[]},{"id":27925,"c":"jeresources.worldgen","cn":"Worldgen","ip":"data/locales/en_us/categories/jeresources.worldgen/recipe_4584.png","o":[{"id":"item:projectred-exploration:stone:0","name":"Marble"}],"in":[]}],"item:projectred-exploration:stone:1":[{"id":23526,"c":"jeresources.worldgen","cn":"Worldgen","ip":"data/locales/en_us/categories/jeresources.worldgen/recipe_185.png","o":[{"id":"item:projectred-exploration:stone:1","name":"Marble Brick"}],"in":[]},{"id":52827,"c":"minecraft.crafting","cn":"Crafting","ip":"data/locales/en_us/categories/minecraft.crafting/recipe_28874.png","o":[{"id":"item:projectred-exploration:stone:1","qty":4,"name":"Marble Brick"}],"in":[{"id":"item:chisel:marble:4","qty":4,"name":"Marble"}]},{"id":61607,"c":"minecraft.crafting","cn":"Crafting","ip":"data/locales/en_us/categories/minecraft.crafting/recipe_9238.png","o":[{"id":"item:projectred-exploration:stone:1","qty":4,"name":"Marble Brick"}],"in":[{"id":"item:chisel:marble:1","qty":4,"name":"Marble"}]}],"item:projectred-exploration:stone:2":[{"id":24556,"c":"jeresources.worldgen","cn":"Worldgen","ip":"data/locales/en_us/categories/jeresources.worldgen/recipe_1215.png","o":[{"id":"item:projectred-exploration:stone:3","name":"Basalt"},{"id":"item:projectred-exploration:stone:2","name":"Basalt Cobblestone"}],"in":[]}],"item:projectred-exploration:ruby_helmet":[{"id":44674,"c":"minecraft.crafting","cn":"Crafting","ip":"data/locales/en_us/categories/minecraft.crafting/recipe_20721.png","o":[{"id":"item:projectred-exploration:ruby_helmet","name":"Ruby Helmet"}],"in":[{"id":"item:projectred-exploration:ruby_helmet","qty":1,"name":"Ruby Helmet"},{"id":"item:nuclearcraft:rad_shielding:0","qty":1,"name":"Light Radiation Shielding"}]},{"id":44675,"c":"minecraft.crafting","cn":"Crafting","ip":"data/locales/en_us/categories/minecraft.crafting/recipe_20722.png","o":[{"id":"item:projectred-exploration:ruby_helmet","name":"Ruby Helmet"}],"in":[{"id":"item:projectred-exploration:ruby_helmet","qty":1,"name":"Ruby Helmet"},{"id":"item:nuclearcraft:rad_shielding:1","qty":1,"name":"Medium Radiation Shielding"}]},{"id":44676,"c":"minecraft.crafting","cn":"Crafting","ip":"data/locales/en_us/categories/minecraft.crafting/recipe_20723.png","o":[{"id":"item:projectred-exploration:ruby_helmet","name":"Ruby Helmet"}],"in":[{"id":"item:projectred-exploration:ruby_helmet","qty":1,"name":"Ruby Helmet"},{"id":"item:nuclearcraft:rad_shielding:2","qty":1,"name":"Heavy Radiation Shielding"}]},{"id":55699,"c":"minecraft.crafting","cn":"Crafting","ip":"data/locales/en_us/categories/minecraft.crafting/recipe_30746.png","o":[{"id":"item:projectred-exploration:ruby_helmet","name":"Ruby Helmet"}],"in":[{"id":"item:projectred-core:resource_item:200","qty":4,"name":"Ruby"},{"id":"item:biomesoplenty:gem_block:1","qty":1,"name":"Block of Ruby"}]},{"id":91592,"c":"zmaster587.AR.chemicalReactor","cn":"Chemicalreactor","ip":"data/locales/en_us/categories/zmaster587.AR.chemicalReactor/recipe_140.png","o":[{"id":"item:projectred-exploration:ruby_helmet","name":"Ruby Helmet"}],"in":[{"id":"item:projectred-exploration:ruby_helmet","qty":1,"name":"Ruby Helmet"},{"id":"item:advancedrocketry:pipesealer","qty":1,"name":"Pipe Seal"},{"id":"item:advancedrocketry:productsheet:0","qty":4,"name":"Titanium Aluminide Sheet"}]}],"item:projectred-exploration:ruby_chestplate":[{"id":44677,"c":"minecraft.crafting","cn":"Crafting","ip":"data/locales/en_us/categories/minecraft.crafting/recipe_20724.png","o":[{"id":"item:projectred-exploration:ruby_chestplate","name":"Ruby Chestplate"}],"in":[{"id":"item:projectred-exploration:ruby_chestplate","qty":1,"name":"Ruby Chestplate"},{"id":"item:nuclearcraft:rad_shielding:0","qty":1,"name":"Light Radiation Shielding"}]},{"id":44678,"c":"minecraft.crafting","cn":"Crafting","ip":"data/locales/en_us/categories/minecraft.crafting/recipe_20725.png","o":[{"id":"item:projectred-exploration:ruby_chestplate","name":"Ruby Chestplate"}],"in":[{"id":"item:projectred-exploration:ruby_chestplate","qty":1,"name":"Ruby Chestplate"},{"id":"item:nuclearcraft:rad_shielding:1","qty":1,"name":"Medium Radiation Shielding"}]},{"id":44679,"c":"minecraft.crafting","cn":"Crafting","ip":"data/locales/en_us/categories/minecraft.crafting/recipe_20726.png","o":[{"id":"item:projectred-exploration:ruby_chestplate","name":"Ruby Chestplate"}],"in":[{"id":"item:projectred-exploration:ruby_chestplate","qty":1,"name":"Ruby Chestplate"},{"id":"item:nuclearcraft:rad_shielding:2","qty":1,"name":"Heavy Radiation Shielding"}]},{"id":55700,"c":"minecraft.crafting","cn":"Crafting","ip":"data/locales/en_us/categories/minecraft.crafting/recipe_30747.png","o":[{"id":"item:projectred-exploration:ruby_chestplate","name":"Ruby Chestplate"}],"in":[{"id":"item:techreborn:gem:0","qty":7,"name":"Reborn Ruby"},{"id":"item:projectred-exploration:stone:5","qty":1,"name":"Block of Ruby"}]},{"id":91593,"c":"zmaster587.AR.chemicalReactor","cn":"Chemicalreactor","ip":"data/locales/en_us/categories/zmaster587.AR.chemicalReactor/recipe_141.png","o":[{"id":"item:projectred-exploration:ruby_chestplate","name":"Ruby Chestplate"}],"in":[{"id":"item:projectred-exploration:ruby_chestplate","qty":1,"name":"Ruby Chestplate"},{"id":"item:advancedrocketry:pipesealer","qty":1,"name":"Pipe Seal"},{"id":"item:advancedrocketry:productsheet:0","qty":4,"name":"Titanium Aluminide Sheet"},{"id":"item:advancedrocketry:pressuretank:empty;m=3","qty":1,"name":"Super High Pressure Tank"}]}],"item:projectred-exploration:ruby_leggings":[{"id":44680,"c":"minecraft.crafting","cn":"Crafting","ip":"data/locales/en_us/categories/minecraft.crafting/recipe_20727.png","o":[{"id":"item:projectred-exploration:ruby_leggings","name":"Ruby Leggings"}],"in":[{"id":"item:projectred-exploration:ruby_leggings","qty":1,"name":"Ruby Leggings"},{"id":"item:nuclearcraft:rad_shielding:0","qty":1,"name":"Light Radiation Shielding"}]},{"id":44681,"c":"minecraft.crafting","cn":"Crafting","ip":"data/locales/en_us/categories/minecraft.crafting/recipe_20728.png","o":[{"id":"item:projectred-exploration:ruby_leggings","name":"Ruby Leggings"}],"in":[{"id":"item:projectred-exploration:ruby_leggings","qty":1,"name":"Ruby Leggings"},{"id":"item:nuclearcraft:rad_shielding:1","qty":1,"name":"Medium Radiation Shielding"}]},{"id":44682,"c":"minecraft.crafting","cn":"Crafting","ip":"data/locales/en_us/categories/minecraft.crafting/recipe_20729.png","o":[{"id":"item:projectred-exploration:ruby_leggings","name":"Ruby Leggings"}],"in":[{"id":"item:projectred-exploration:ruby_leggings","qty":1,"name":"Ruby Leggings"},{"id":"item:nuclearcraft:rad_shielding:2","qty":1,"name":"Heavy Radiation Shielding"}]},{"id":55701,"c":"minecraft.crafting","cn":"Crafting","ip":"data/locales/en_us/categories/minecraft.crafting/recipe_30748.png","o":[{"id":"item:projectred-exploration:ruby_leggings","name":"Ruby Leggings"}],"in":[{"id":"item:biomesoplenty:gem:1","qty":6,"name":"Ruby"},{"id":"item:techreborn:storage2:3","qty":1,"name":"Block of Reborn Ruby"}]},{"id":91594,"c":"zmaster587.AR.chemicalReactor","cn":"Chemicalreactor","ip":"data/locales/en_us/categories/zmaster587.AR.chemicalReactor/recipe_142.png","o":[{"id":"item:projectred-exploration:ruby_leggings","name":"Ruby Leggings"}],"in":[{"id":"item:projectred-exploration:ruby_leggings","qty":1,"name":"Ruby Leggings"},{"id":"item:advancedrocketry:pipesealer","qty":1,"name":"Pipe Seal"},{"id":"item:advancedrocketry:productsheet:0","qty":4,"name":"Titanium Aluminide Sheet"}]}],"item:projectred-exploration:ruby_boots":[{"id":44683,"c":"minecraft.crafting","cn":"Crafting","ip":"data/locales/en_us/categories/minecraft.crafting/recipe_20730.png","o":[{"id":"item:projectred-exploration:ruby_boots","name":"Ruby Boots"}],"in":[{"id":"item:projectred-exploration:ruby_boots","qty":1,"name":"Ruby Boots"},{"id":"item:nuclearcraft:rad_shielding:0","qty":1,"name":"Light Radiation Shielding"}]},{"id":44684,"c":"minecraft.crafting","cn":"Crafting","ip":"data/locales/en_us/categories/minecraft.crafting/recipe_20731.png","o":[{"id":"item:projectred-exploration:ruby_boots","name":"Ruby Boots"}],"in":[{"id":"item:projectred-exploration:ruby_boots","qty":1,"name":"Ruby Boots"},{"id":"item:nuclearcraft:rad_shielding:1","qty":1,"name":"Medium Radiation Shielding"}]},{"id":44685,"c":"minecraft.crafting","cn":"Crafting","ip":"data/locales/en_us/categories/minecraft.crafting/recipe_20732.png","o":[{"id":"item:projectred-exploration:ruby_boots","name":"Ruby Boots"}],"in":[{"id":"item:projectred-exploration:ruby_boots","qty":1,"name":"Ruby Boots"},{"id":"item:nuclearcraft:rad_shielding:2","qty":1,"name":"Heavy Radiation Shielding"}]},{"id":55702,"c":"minecraft.crafting","cn":"Crafting","ip":"data/locales/en_us/categories/minecraft.crafting/recipe_30749.png","o":[{"id":"item:projectred-exploration:ruby_boots","name":"Ruby Boots"}],"in":[{"id":"item:projectred-exploration:stone:5","qty":2,"name":"Block of Ruby"},{"id":"item:techreborn:gem:0","qty":2,"name":"Reborn Ruby"}]},{"id":91595,"c":"zmaster587.AR.chemicalReactor","cn":"Chemicalreactor","ip":"data/locales/en_us/categories/zmaster587.AR.chemicalReactor/recipe_143.png","o":[{"id":"item:projectred-exploration:ruby_boots","name":"Ruby Boots"}],"in":[{"id":"item:projectred-exploration:ruby_boots","qty":1,"name":"Ruby Boots"},{"id":"item:advancedrocketry:pipesealer","qty":1,"name":"Pipe Seal"},{"id":"item:advancedrocketry:productsheet:0","qty":4,"name":"Titanium Aluminide Sheet"}]}],"item:projectred-exploration:sapphire_helmet":[{"id":44686,"c":"minecraft.crafting","cn":"Crafting","ip":"data/locales/en_us/categories/minecraft.crafting/recipe_20733.png","o":[{"id":"item:projectred-exploration:sapphire_helmet","name":"Sapphire Helmet"}],"in":[{"id":"item:projectred-exploration:sapphire_helmet","qty":1,"name":"Sapphire Helmet"},{"id":"item:nuclearcraft:rad_shielding:0","qty":1,"name":"Light Radiation Shielding"}]},{"id":44687,"c":"minecraft.crafting","cn":"Crafting","ip":"data/locales/en_us/categories/minecraft.crafting/recipe_20734.png","o":[{"id":"item:projectred-exploration:sapphire_helmet","name":"Sapphire Helmet"}],"in":[{"id":"item:projectred-exploration:sapphire_helmet","qty":1,"name":"Sapphire Helmet"},{"id":"item:nuclearcraft:rad_shielding:1","qty":1,"name":"Medium Radiation Shielding"}]},{"id":44688,"c":"minecraft.crafting","cn":"Crafting","ip":"data/locales/en_us/categories/minecraft.crafting/recipe_20735.png","o":[{"id":"item:projectred-exploration:sapphire_helmet","name":"Sapphire Helmet"}],"in":[{"id":"item:projectred-exploration:sapphire_helmet","qty":1,"name":"Sapphire Helmet"},{"id":"item:nuclearcraft:rad_shielding:2","qty":1,"name":"Heavy Radiation Shielding"}]},{"id":55695,"c":"minecraft.crafting","cn":"Crafting","ip":"data/locales/en_us/categories/minecraft.crafting/recipe_30742.png","o":[{"id":"item:projectred-exploration:sapphire_helmet","name":"Sapphire Helmet"}],"in":[{"id":"item:projectred-core:resource_item:201","qty":4,"name":"Sapphire"},{"id":"item:biomesoplenty:gem_block:6","qty":1,"name":"Block of Sapphire"}]},{"id":91596,"c":"zmaster587.AR.chemicalReactor","cn":"Chemicalreactor","ip":"data/locales/en_us/categories/zmaster587.AR.chemicalReactor/recipe_144.png","o":[{"id":"item:projectred-exploration:sapphire_helmet","name":"Sapphire Helmet"}],"in":[{"id":"item:projectred-exploration:sapphire_helmet","qty":1,"name":"Sapphire Helmet"},{"id":"item:advancedrocketry:pipesealer","qty":1,"name":"Pipe Seal"},{"id":"item:advancedrocketry:productsheet:0","qty":4,"name":"Titanium Aluminide Sheet"}]}],"item:projectred-exploration:sapphire_chestplate":[{"id":44689,"c":"minecraft.crafting","cn":"Crafting","ip":"data/locales/en_us/categories/minecraft.crafting/recipe_20736.png","o":[{"id":"item:projectred-exploration:sapphire_chestplate","name":"Sapphire Chestplate"}],"in":[{"id":"item:projectred-exploration:sapphire_chestplate","qty":1,"name":"Sapphire Chestplate"},{"id":"item:nuclearcraft:rad_shielding:0","qty":1,"name":"Light Radiation Shielding"}]},{"id":44690,"c":"minecraft.crafting","cn":"Crafting","ip":"data/locales/en_us/categories/minecraft.crafting/recipe_20737.png","o":[{"id":"item:projectred-exploration:sapphire_chestplate","name":"Sapphire Chestplate"}],"in":[{"id":"item:projectred-exploration:sapphire_chestplate","qty":1,"name":"Sapphire Chestplate"},{"id":"item:nuclearcraft:rad_shielding:1","qty":1,"name":"Medium Radiation Shielding"}]},{"id":44691,"c":"minecraft.crafting","cn":"Crafting","ip":"data/locales/en_us/categories/minecraft.crafting/recipe_20738.png","o":[{"id":"item:projectred-exploration:sapphire_chestplate","name":"Sapphire Chestplate"}],"in":[{"id":"item:projectred-exploration:sapphire_chestplate","qty":1,"name":"Sapphire Chestplate"},{"id":"item:nuclearcraft:rad_shielding:2","qty":1,"name":"Heavy Radiation Shielding"}]},{"id":55696,"c":"minecraft.crafting","cn":"Crafting","ip":"data/locales/en_us/categories/minecraft.crafting/recipe_30743.png","o":[{"id":"item:projectred-exploration:sapphire_chestplate","name":"Sapphire Chestplate"}],"in":[{"id":"item:biomesoplenty:gem:6","qty":7,"name":"Sapphire"},{"id":"item:techreborn:storage2:4","qty":1,"name":"Block of Reborn Sapphire"}]},{"id":91597,"c":"zmaster587.AR.chemicalReactor","cn":"Chemicalreactor","ip":"data/locales/en_us/categories/zmaster587.AR.chemicalReactor/recipe_145.png","o":[{"id":"item:projectred-exploration:sapphire_chestplate","name":"Sapphire Chestplate"}],"in":[{"id":"item:projectred-exploration:sapphire_chestplate","qty":1,"name":"Sapphire Chestplate"},{"id":"item:advancedrocketry:pipesealer","qty":1,"name":"Pipe Seal"},{"id":"item:advancedrocketry:productsheet:0","qty":4,"name":"Titanium Aluminide Sheet"},{"id":"item:advancedrocketry:pressuretank:empty;m=3","qty":1,"name":"Super High Pressure Tank"}]}],"item:projectred-exploration:sapphire_leggings":[{"id":44692,"c":"minecraft.crafting","cn":"Crafting","ip":"data/locales/en_us/categories/minecraft.crafting/recipe_20739.png","o":[{"id":"item:projectred-exploration:sapphire_leggings","name":"Sapphire Leggings"}],"in":[{"id":"item:projectred-exploration:sapphire_leggings","qty":1,"name":"Sapphire Leggings"},{"id":"item:nuclearcraft:rad_shielding:0","qty":1,"name":"Light Radiation Shielding"}]},{"id":44693,"c":"minecraft.crafting","cn":"Crafting","ip":"data/locales/en_us/categories/minecraft.crafting/recipe_20740.png","o":[{"id":"item:projectred-exploration:sapphire_leggings","name":"Sapphire Leggings"}],"in":[{"id":"item:projectred-exploration:sapphire_leggings","qty":1,"name":"Sapphire Leggings"},{"id":"item:nuclearcraft:rad_shielding:1","qty":1,"name":"Medium Radiation Shielding"}]},{"id":44694,"c":"minecraft.crafting","cn":"Crafting","ip":"data/locales/en_us/categories/minecraft.crafting/recipe_20741.png","o":[{"id":"item:projectred-exploration:sapphire_leggings","name":"Sapphire Leggings"}],"in":[{"id":"item:projectred-exploration:sapphire_leggings","qty":1,"name":"Sapphire Leggings"},{"id":"item:nuclearcraft:rad_shielding:2","qty":1,"name":"Heavy Radiation Shielding"}]},{"id":55697,"c":"minecraft.crafting","cn":"Crafting","ip":"data/locales/en_us/categories/minecraft.crafting/recipe_30744.png","o":[{"id":"item:projectred-exploration:sapphire_leggings","name":"Sapphire Leggings"}],"in":[{"id":"item:techreborn:gem:1","qty":6,"name":"Reborn Sapphire"},{"id":"item:iceandfire:sapphire_block","qty":1,"name":"Singing Sapphire Block"}]},{"id":91598,"c":"zmaster587.AR.chemicalReactor","cn":"Chemicalreactor","ip":"data/locales/en_us/categories/zmaster587.AR.chemicalReactor/recipe_146.png","o":[{"id":"item:projectred-exploration:sapphire_leggings","name":"Sapphire Leggings"}],"in":[{"id":"item:projectred-exploration:sapphire_leggings","qty":1,"name":"Sapphire Leggings"},{"id":"item:advancedrocketry:pipesealer","qty":1,"name":"Pipe Seal"},{"id":"item:advancedrocketry:productsheet:0","qty":4,"name":"Titanium Aluminide Sheet"}]}],"item:projectred-exploration:sapphire_boots":[{"id":44695,"c":"minecraft.crafting","cn":"Crafting","ip":"data/locales/en_us/categories/minecraft.crafting/recipe_20742.png","o":[{"id":"item:projectred-exploration:sapphire_boots","name":"Sapphire Boots"}],"in":[{"id":"item:projectred-exploration:sapphire_boots","qty":1,"name":"Sapphire Boots"},{"id":"item:nuclearcraft:rad_shielding:0","qty":1,"name":"Light Radiation Shielding"}]},{"id":44696,"c":"minecraft.crafting","cn":"Crafting","ip":"data/locales/en_us/categories/minecraft.crafting/recipe_20743.png","o":[{"id":"item:projectred-exploration:sapphire_boots","name":"Sapphire Boots"}],"in":[{"id":"item:projectred-exploration:sapphire_boots","qty":1,"name":"Sapphire Boots"},{"id":"item:nuclearcraft:rad_shielding:1","qty":1,"name":"Medium Radiation Shielding"}]},{"id":44697,"c":"minecraft.crafting","cn":"Crafting","ip":"data/locales/en_us/categories/minecraft.crafting/recipe_20744.png","o":[{"id":"item:projectred-exploration:sapphire_boots","name":"Sapphire Boots"}],"in":[{"id":"item:projectred-exploration:sapphire_boots","qty":1,"name":"Sapphire Boots"},{"id":"item:nuclearcraft:rad_shielding:2","qty":1,"name":"Heavy Radiation Shielding"}]},{"id":55698,"c":"minecraft.crafting","cn":"Crafting","ip":"data/locales/en_us/categories/minecraft.crafting/recipe_30745.png","o":[{"id":"item:projectred-exploration:sapphire_boots","name":"Sapphire Boots"}],"in":[{"id":"item:iceandfire:sapphire_block","qty":2,"name":"Singing Sapphire Block"},{"id":"item:techreborn:gem:1","qty":2,"name":"Reborn Sapphire"}]},{"id":91599,"c":"zmaster587.AR.chemicalReactor","cn":"Chemicalreactor","ip":"data/locales/en_us/categories/zmaster587.AR.chemicalReactor/recipe_147.png","o":[{"id":"item:projectred-exploration:sapphire_boots","name":"Sapphire Boots"}],"in":[{"id":"item:projectred-exploration:sapphire_boots","qty":1,"name":"Sapphire Boots"},{"id":"item:advancedrocketry:pipesealer","qty":1,"name":"Pipe Seal"},{"id":"item:advancedrocketry:productsheet:0","qty":4,"name":"Titanium Aluminide Sheet"}]}],"item:projectred-exploration:peridot_helmet":[{"id":44698,"c":"minecraft.crafting","cn":"Crafting","ip":"data/locales/en_us/categories/minecraft.crafting/recipe_20745.png","o":[{"id":"item:projectred-exploration:peridot_helmet","name":"Peridot Helmet"}],"in":[{"id":"item:projectred-exploration:peridot_helmet","qty":1,"name":"Peridot Helmet"},{"id":"item:nuclearcraft:rad_shielding:0","qty":1,"name":"Light Radiation Shielding"}]},{"id":44699,"c":"minecraft.crafting","cn":"Crafting","ip":"data/locales/en_us/categories/minecraft.crafting/recipe_20746.png","o":[{"id":"item:projectred-exploration:peridot_helmet","name":"Peridot Helmet"}],"in":[{"id":"item:projectred-exploration:peridot_helmet","qty":1,"name":"Peridot Helmet"},{"id":"item:nuclearcraft:rad_shielding:1","qty":1,"name":"Medium Radiation Shielding"}]},{"id":44700,"c":"minecraft.crafting","cn":"Crafting","ip":"data/locales/en_us/categories/minecraft.crafting/recipe_20747.png","o":[{"id":"item:projectred-exploration:peridot_helmet","name":"Peridot Helmet"}],"in":[{"id":"item:projectred-exploration:peridot_helmet","qty":1,"name":"Peridot Helmet"},{"id":"item:nuclearcraft:rad_shielding:2","qty":1,"name":"Heavy Radiation Shielding"}]},{"id":55703,"c":"minecraft.crafting","cn":"Crafting","ip":"data/locales/en_us/categories/minecraft.crafting/recipe_30750.png","o":[{"id":"item:projectred-exploration:peridot_helmet","name":"Peridot Helmet"}],"in":[{"id":"item:projectred-core:resource_item:202","qty":4,"name":"Peridot"},{"id":"item:biomesoplenty:gem_block:2","qty":1,"name":"Block of Peridot"}]},{"id":91600,"c":"zmaster587.AR.chemicalReactor","cn":"Chemicalreactor","ip":"data/locales/en_us/categories/zmaster587.AR.chemicalReactor/recipe_148.png","o":[{"id":"item:projectred-exploration:peridot_helmet","name":"Peridot Helmet"}],"in":[{"id":"item:projectred-exploration:peridot_helmet","qty":1,"name":"Peridot Helmet"},{"id":"item:advancedrocketry:pipesealer","qty":1,"name":"Pipe Seal"},{"id":"item:advancedrocketry:productsheet:0","qty":4,"name":"Titanium Aluminide Sheet"}]}],"item:projectred-exploration:peridot_chestplate":[{"id":44701,"c":"minecraft.crafting","cn":"Crafting","ip":"data/locales/en_us/categories/minecraft.crafting/recipe_20748.png","o":[{"id":"item:projectred-exploration:peridot_chestplate","name":"Peridot Chestplate"}],"in":[{"id":"item:projectred-exploration:peridot_chestplate","qty":1,"name":"Peridot Chestplate"},{"id":"item:nuclearcraft:rad_shielding:0","qty":1,"name":"Light Radiation Shielding"}]},{"id":44702,"c":"minecraft.crafting","cn":"Crafting","ip":"data/locales/en_us/categories/minecraft.crafting/recipe_20749.png","o":[{"id":"item:projectred-exploration:peridot_chestplate","name":"Peridot Chestplate"}],"in":[{"id":"item:projectred-exploration:peridot_chestplate","qty":1,"name":"Peridot Chestplate"},{"id":"item:nuclearcraft:rad_shielding:1","qty":1,"name":"Medium Radiation Shielding"}]},{"id":44703,"c":"minecraft.crafting","cn":"Crafting","ip":"data/locales/en_us/categories/minecraft.crafting/recipe_20750.png","o":[{"id":"item:projectred-exploration:peridot_chestplate","name":"Peridot Chestplate"}],"in":[{"id":"item:projectred-exploration:peridot_chestplate","qty":1,"name":"Peridot Chestplate"},{"id":"item:nuclearcraft:rad_shielding:2","qty":1,"name":"Heavy Radiation Shielding"}]},{"id":55704,"c":"minecraft.crafting","cn":"Crafting","ip":"data/locales/en_us/categories/minecraft.crafting/recipe_30751.png","o":[{"id":"item:projectred-exploration:peridot_chestplate","name":"Peridot Chestplate"}],"in":[{"id":"item:projectred-core:resource_item:202","qty":7,"name":"Peridot"},{"id":"item:biomesoplenty:gem_block:2","qty":1,"name":"Block of Peridot"}]},{"id":91601,"c":"zmaster587.AR.chemicalReactor","cn":"Chemicalreactor","ip":"data/locales/en_us/categories/zmaster587.AR.chemicalReactor/recipe_149.png","o":[{"id":"item:projectred-exploration:peridot_chestplate","name":"Peridot Chestplate"}],"in":[{"id":"item:projectred-exploration:peridot_chestplate","qty":1,"name":"Peridot Chestplate"},{"id":"item:advancedrocketry:pipesealer","qty":1,"name":"Pipe Seal"},{"id":"item:advancedrocketry:productsheet:0","qty":4,"name":"Titanium Aluminide Sheet"},{"id":"item:advancedrocketry:pressuretank:empty;m=3","qty":1,"name":"Super High Pressure Tank"}]}],"item:projectred-exploration:peridot_leggings":[{"id":44704,"c":"minecraft.crafting","cn":"Crafting","ip":"data/locales/en_us/categories/minecraft.crafting/recipe_20751.png","o":[{"id":"item:projectred-exploration:peridot_leggings","name":"Peridot Leggings"}],"in":[{"id":"item:projectred-exploration:peridot_leggings","qty":1,"name":"Peridot Leggings"},{"id":"item:nuclearcraft:rad_shielding:0","qty":1,"name":"Light Radiation Shielding"}]},{"id":44705,"c":"minecraft.crafting","cn":"Crafting","ip":"data/locales/en_us/categories/minecraft.crafting/recipe_20752.png","o":[{"id":"item:projectred-exploration:peridot_leggings","name":"Peridot Leggings"}],"in":[{"id":"item:projectred-exploration:peridot_leggings","qty":1,"name":"Peridot Leggings"},{"id":"item:nuclearcraft:rad_shielding:1","qty":1,"name":"Medium Radiation Shielding"}]},{"id":44706,"c":"minecraft.crafting","cn":"Crafting","ip":"data/locales/en_us/categories/minecraft.crafting/recipe_20753.png","o":[{"id":"item:projectred-exploration:peridot_leggings","name":"Peridot Leggings"}],"in":[{"id":"item:projectred-exploration:peridot_leggings","qty":1,"name":"Peridot Leggings"},{"id":"item:nuclearcraft:rad_shielding:2","qty":1,"name":"Heavy Radiation Shielding"}]},{"id":55705,"c":"minecraft.crafting","cn":"Crafting","ip":"data/locales/en_us/categories/minecraft.crafting/recipe_30752.png","o":[{"id":"item:projectred-exploration:peridot_leggings","name":"Peridot Leggings"}],"in":[{"id":"item:projectred-core:resource_item:202","qty":6,"name":"Peridot"},{"id":"item:biomesoplenty:gem_block:2","qty":1,"name":"Block of Peridot"}]},{"id":91602,"c":"zmaster587.AR.chemicalReactor","cn":"Chemicalreactor","ip":"data/locales/en_us/categories/zmaster587.AR.chemicalReactor/recipe_150.png","o":[{"id":"item:projectred-exploration:peridot_leggings","name":"Peridot Leggings"}],"in":[{"id":"item:projectred-exploration:peridot_leggings","qty":1,"name":"Peridot Leggings"},{"id":"item:advancedrocketry:pipesealer","qty":1,"name":"Pipe Seal"},{"id":"item:advancedrocketry:productsheet:0","qty":4,"name":"Titanium Aluminide Sheet"}]}],"item:projectred-exploration:peridot_boots":[{"id":44707,"c":"minecraft.crafting","cn":"Crafting","ip":"data/locales/en_us/categories/minecraft.crafting/recipe_20754.png","o":[{"id":"item:projectred-exploration:peridot_boots","name":"Peridot Boots"}],"in":[{"id":"item:projectred-exploration:peridot_boots","qty":1,"name":"Peridot Boots"},{"id":"item:nuclearcraft:rad_shielding:0","qty":1,"name":"Light Radiation Shielding"}]},{"id":44708,"c":"minecraft.crafting","cn":"Crafting","ip":"data/locales/en_us/categories/minecraft.crafting/recipe_20755.png","o":[{"id":"item:projectred-exploration:peridot_boots","name":"Peridot Boots"}],"in":[{"id":"item:projectred-exploration:peridot_boots","qty":1,"name":"Peridot Boots"},{"id":"item:nuclearcraft:rad_shielding:1","qty":1,"name":"Medium Radiation Shielding"}]},{"id":44709,"c":"minecraft.crafting","cn":"Crafting","ip":"data/locales/en_us/categories/minecraft.crafting/recipe_20756.png","o":[{"id":"item:projectred-exploration:peridot_boots","name":"Peridot Boots"}],"in":[{"id":"item:projectred-exploration:peridot_boots","qty":1,"name":"Peridot Boots"},{"id":"item:nuclearcraft:rad_shielding:2","qty":1,"name":"Heavy Radiation Shielding"}]},{"id":55706,"c":"minecraft.crafting","cn":"Crafting","ip":"data/locales/en_us/categories/minecraft.crafting/recipe_30753.png","o":[{"id":"item:projectred-exploration:peridot_boots","name":"Peridot Boots"}],"in":[{"id":"item:biomesoplenty:gem_block:2","qty":2,"name":"Block of Peridot"},{"id":"item:projectred-core:resource_item:202","qty":2,"name":"Peridot"}]},{"id":91603,"c":"zmaster587.AR.chemicalReactor","cn":"Chemicalreactor","ip":"data/locales/en_us/categories/zmaster587.AR.chemicalReactor/recipe_151.png","o":[{"id":"item:projectred-exploration:peridot_boots","name":"Peridot Boots"}],"in":[{"id":"item:projectred-exploration:peridot_boots","qty":1,"name":"Peridot Boots"},{"id":"item:advancedrocketry:pipesealer","qty":1,"name":"Pipe Seal"},{"id":"item:advancedrocketry:productsheet:0","qty":4,"name":"Titanium Aluminide Sheet"}]}],"item:projectred-exploration:sapphire_pickaxe":[{"id":51543,"c":"minecraft.crafting","cn":"Crafting","ip":"data/locales/en_us/categories/minecraft.crafting/recipe_27590.png","o":[{"id":"item:projectred-exploration:sapphire_pickaxe","name":"Sapphire Pickaxe"}],"in":[{"id":"item:techreborn:sapphirepickaxe","qty":1,"name":"Reborn Sapphire Pickaxe"}]},{"id":61532,"c":"minecraft.crafting","cn":"Crafting","ip":"data/locales/en_us/categories/minecraft.crafting/recipe_9163.png","o":[{"id":"item:projectred-exploration:sapphire_pickaxe","name":"Sapphire Pickaxe"}],"in":[{"id":"item:techreborn:gem:1","qty":3,"name":"Reborn Sapphire"},{"id":"item:natura:sticks:11","qty":2,"name":"Fusewood Sticks"}]}],"item:projectred-exploration:sapphire_axe":[{"id":51544,"c":"minecraft.crafting","cn":"Crafting","ip":"data/locales/en_us/categories/minecraft.crafting/recipe_27591.png","o":[{"id":"item:projectred-exploration:sapphire_axe","name":"Sapphire Axe"}],"in":[{"id":"item:techreborn:sapphireaxe","qty":1,"name":"Reborn Sapphire Axe"}]},{"id":61534,"c":"minecraft.crafting","cn":"Crafting","ip":"data/locales/en_us/categories/minecraft.crafting/recipe_9165.png","o":[{"id":"item:projectred-exploration:sapphire_axe","name":"Sapphire Axe"}],"in":[{"id":"item:techreborn:gem:1","qty":3,"name":"Reborn Sapphire"},{"id":"item:natura:sticks:0","qty":2,"name":"Maple Sticks"}]}],"item:projectred-exploration:sapphire_shovel":[{"id":51547,"c":"minecraft.crafting","cn":"Crafting","ip":"data/locales/en_us/categories/minecraft.crafting/recipe_27594.png","o":[{"id":"item:projectred-exploration:sapphire_shovel","name":"Sapphire Shovel"}],"in":[{"id":"item:techreborn:sapphirespade","qty":1,"name":"Reborn Sapphire Shovel"}]},{"id":61530,"c":"minecraft.crafting","cn":"Crafting","ip":"data/locales/en_us/categories/minecraft.crafting/recipe_9161.png","o":[{"id":"item:projectred-exploration:sapphire_shovel","name":"Sapphire Shovel"}],"in":[{"id":"item:iceandfire:sapphire_gem","qty":1,"name":"Singing Sapphire"},{"id":"item:natura:sticks:10","qty":2,"name":"Darkwood Sticks"}]}],"item:projectred-exploration:sapphire_hoe":[{"id":51548,"c":"minecraft.crafting","cn":"Crafting","ip":"data/locales/en_us/categories/minecraft.crafting/recipe_27595.png","o":[{"id":"item:projectred-exploration:sapphire_hoe","name":"Sapphire Hoe"}],"in":[{"id":"item:techreborn:sapphirehoe","qty":1,"name":"Reborn Sapphire Hoe"}]},{"id":61533,"c":"minecraft.crafting","cn":"Crafting","ip":"data/locales/en_us/categories/minecraft.crafting/recipe_9164.png","o":[{"id":"item:projectred-exploration:sapphire_hoe","name":"Sapphire Hoe"}],"in":[{"id":"item:iceandfire:sapphire_gem","qty":2,"name":"Singing Sapphire"},{"id":"item:natura:sticks:0","qty":2,"name":"Maple Sticks"}]}],"item:projectred-exploration:sapphire_sword":[{"id":51551,"c":"minecraft.crafting","cn":"Crafting","ip":"data/locales/en_us/categories/minecraft.crafting/recipe_27598.png","o":[{"id":"item:projectred-exploration:sapphire_sword","name":"Sapphire Sword"}],"in":[{"id":"item:techreborn:sapphiresword","qty":1,"name":"Reborn Sapphire Sword"}]},{"id":61528,"c":"minecraft.crafting","cn":"Crafting","ip":"data/locales/en_us/categories/minecraft.crafting/recipe_9159.png","o":[{"id":"item:projectred-exploration:sapphire_sword","name":"Sapphire Sword"}],"in":[{"id":"item:iceandfire:sapphire_gem","qty":2,"name":"Singing Sapphire"},{"id":"item:natura:sticks:10","qty":1,"name":"Darkwood Sticks"}]}],"item:projectred-exploration:wool_gin":[{"id":61525,"c":"minecraft.crafting","cn":"Crafting","ip":"data/locales/en_us/categories/minecraft.crafting/recipe_9156.png","o":[{"id":"item:projectred-exploration:wool_gin","name":"Wool Gin"}],"in":[{"id":"item:aether_legacy:skyroot_stick","qty":6,"name":"Skyroot Stick"},{"id":"item:projectred-core:resource_item:401","qty":1,"name":"Iron Coil"}]}],"item:projectred-exploration:wooden_sickle":[{"id":61526,"c":"minecraft.crafting","cn":"Crafting","ip":"data/locales/en_us/categories/minecraft.crafting/recipe_9157.png","o":[{"id":"item:projectred-exploration:wooden_sickle","name":"Wooden Sickle"}],"in":[{"id":"item:forestry:planks.1:10","qty":3,"name":"Padauk Wood Planks"},{"id":"item:natura:sticks:11","qty":1,"name":"Fusewood Sticks"}]}],"item:projectred-exploration:stone_sickle":[{"id":61527,"c":"minecraft.crafting","cn":"Crafting","ip":"data/locales/en_us/categories/minecraft.crafting/recipe_9158.png","o":[{"id":"item:projectred-exploration:stone_sickle","name":"Stone Sickle"}],"in":[{"id":"item:minecraft:flint","qty":3,"name":"Flint"},{"id":"item:thebetweenlands:items_misc:20","qty":1,"name":"Weedwood Stick"}]}],"item:projectred-exploration:sapphire_sickle":[{"id":61529,"c":"minecraft.crafting","cn":"Crafting","ip":"data/locales/en_us/categories/minecraft.crafting/recipe_9160.png","o":[{"id":"item:projectred-exploration:sapphire_sickle","name":"Sapphire Sickle"}],"in":[{"id":"item:iceandfire:sapphire_gem","qty":3,"name":"Singing Sapphire"},{"id":"item:minecraft:stick","qty":1,"name":"Stick"}]}],"item:projectred-exploration:sapphire_saw":[{"id":61531,"c":"minecraft.crafting","cn":"Crafting","ip":"data/locales/en_us/categories/minecraft.crafting/recipe_9162.png","o":[{"id":"item:projectred-exploration:sapphire_saw","name":"Sapphire Saw"}],"in":[{"id":"item:natura:sticks:2","qty":2,"name":"Amaranth Sticks"},{"id":"item:microblockcbe:stone_rod","qty":2,"name":"Stone Rod"},{"id":"item:biomesoplenty:gem:6","qty":2,"name":"Sapphire"}]}],"item:projectred-exploration:ruby_sword":[{"id":61535,"c":"minecraft.crafting","cn":"Crafting","ip":"data/locales/en_us/categories/minecraft.crafting/recipe_9166.png","o":[{"id":"item:projectred-exploration:ruby_sword","name":"Ruby Sword"}],"in":[{"id":"item:techreborn:gem:0","qty":2,"name":"Reborn Ruby"},{"id":"item:natura:sticks:6","qty":1,"name":"Hopseed Sticks"}]}],"item:projectred-exploration:ruby_sickle":[{"id":61536,"c":"minecraft.crafting","cn":"Crafting","ip":"data/locales/en_us/categories/minecraft.crafting/recipe_9167.png","o":[{"id":"item:projectred-exploration:ruby_sickle","name":"Ruby Sickle"}],"in":[{"id":"item:biomesoplenty:gem:1","qty":3,"name":"Ruby"},{"id":"item:natura:sticks:7","qty":1,"name":"Sakura Sticks"}]}],"item:projectred-exploration:ruby_shovel":[{"id":61537,"c":"minecraft.crafting","cn":"Crafting","ip":"data/locales/en_us/categories/minecraft.crafting/recipe_9168.png","o":[{"id":"item:projectred-exploration:ruby_shovel","name":"Ruby Shovel"}],"in":[{"id":"item:biomesoplenty:gem:1","qty":1,"name":"Ruby"},{"id":"item:natura:sticks:9","qty":2,"name":"Ghostwood Sticks"}]}],"item:projectred-exploration:ruby_saw":[{"id":61538,"c":"minecraft.crafting","cn":"Crafting","ip":"data/locales/en_us/categories/minecraft.crafting/recipe_9169.png","o":[{"id":"item:projectred-exploration:ruby_saw","name":"Ruby Saw"}],"in":[{"id":"item:natura:sticks:2","qty":2,"name":"Amaranth Sticks"},{"id":"item:microblockcbe:stone_rod","qty":2,"name":"Stone Rod"},{"id":"item:biomesoplenty:gem:1","qty":2,"name":"Ruby"}]}],"item:projectred-exploration:ruby_pickaxe":[{"id":61539,"c":"minecraft.crafting","cn":"Crafting","ip":"data/locales/en_us/categories/minecraft.crafting/recipe_9170.png","o":[{"id":"item:projectred-exploration:ruby_pickaxe","name":"Ruby Pickaxe"}],"in":[{"id":"item:techreborn:gem:0","qty":3,"name":"Reborn Ruby"},{"id":"item:thebetweenlands:items_misc:20","qty":2,"name":"Weedwood Stick"}]}],"item:projectred-exploration:ruby_hoe":[{"id":61540,"c":"minecraft.crafting","cn":"Crafting","ip":"data/locales/en_us/categories/minecraft.crafting/recipe_9171.png","o":[{"id":"item:projectred-exploration:ruby_hoe","name":"Ruby Hoe"}],"in":[{"id":"item:techreborn:gem:0","qty":2,"name":"Reborn Ruby"},{"id":"item:natura:sticks:9","qty":2,"name":"Ghostwood Sticks"}]}],"item:projectred-exploration:ruby_axe":[{"id":61541,"c":"minecraft.crafting","cn":"Crafting","ip":"data/locales/en_us/categories/minecraft.crafting/recipe_9172.png","o":[{"id":"item:projectred-exploration:ruby_axe","name":"Ruby Axe"}],"in":[{"id":"item:techreborn:gem:0","qty":3,"name":"Reborn Ruby"},{"id":"item:natura:sticks:8","qty":2,"name":"Redwood Sticks"}]}],"item:projectred-exploration:peridot_sword":[{"id":61542,"c":"minecraft.crafting","cn":"Crafting","ip":"data/locales/en_us/categories/minecraft.crafting/recipe_9173.png","o":[{"id":"item:projectred-exploration:peridot_sword","name":"Peridot Sword"}],"in":[{"id":"item:techreborn:gem:2","qty":2,"name":"Reborn Peridot"},{"id":"item:natura:sticks:0","qty":1,"name":"Maple Sticks"}]}],"item:projectred-exploration:peridot_sickle":[{"id":61543,"c":"minecraft.crafting","cn":"Crafting","ip":"data/locales/en_us/categories/minecraft.crafting/recipe_9174.png","o":[{"id":"item:projectred-exploration:peridot_sickle","name":"Peridot Sickle"}],"in":[{"id":"item:projectred-core:resource_item:202","qty":3,"name":"Peridot"},{"id":"item:natura:sticks:5","qty":1,"name":"Eucalyptus Sticks"}]}],"item:projectred-exploration:peridot_shovel":[{"id":61544,"c":"minecraft.crafting","cn":"Crafting","ip":"data/locales/en_us/categories/minecraft.crafting/recipe_9175.png","o":[{"id":"item:projectred-exploration:peridot_shovel","name":"Peridot Shovel"}],"in":[{"id":"item:techreborn:gem:2","qty":1,"name":"Reborn Peridot"},{"id":"item:minecraft:stick","qty":2,"name":"Stick"}]}],"item:projectred-exploration:peridot_saw":[{"id":61545,"c":"minecraft.crafting","cn":"Crafting","ip":"data/locales/en_us/categories/minecraft.crafting/recipe_9176.png","o":[{"id":"item:projectred-exploration:peridot_saw","name":"Peridot Saw"}],"in":[{"id":"item:natura:sticks:1","qty":2,"name":"Silverbell Sticks"},{"id":"item:tconstruct:stone_stick","qty":2,"name":"Stone Rod"},{"id":"item:projectred-core:resource_item:202","qty":2,"name":"Peridot"}]}],"item:projectred-exploration:peridot_pickaxe":[{"id":61546,"c":"minecraft.crafting","cn":"Crafting","ip":"data/locales/en_us/categories/minecraft.crafting/recipe_9177.png","o":[{"id":"item:projectred-exploration:peridot_pickaxe","name":"Peridot Pickaxe"}],"in":[{"id":"item:projectred-core:resource_item:202","qty":3,"name":"Peridot"},{"id":"item:natura:sticks:12","qty":2,"name":"Bloodwood Sticks"}]}],"item:projectred-exploration:peridot_hoe":[{"id":61547,"c":"minecraft.crafting","cn":"Crafting","ip":"data/locales/en_us/categories/minecraft.crafting/recipe_9178.png","o":[{"id":"item:projectred-exploration:peridot_hoe","name":"Peridot Hoe"}],"in":[{"id":"item:techreborn:gem:2","qty":2,"name":"Reborn Peridot"},{"id":"item:natura:sticks:1","qty":2,"name":"Silverbell Sticks"}]}],"item:projectred-exploration:peridot_axe":[{"id":61548,"c":"minecraft.crafting","cn":"Crafting","ip":"data/locales/en_us/categories/minecraft.crafting/recipe_9179.png","o":[{"id":"item:projectred-exploration:peridot_axe","name":"Peridot Axe"}],"in":[{"id":"item:biomesoplenty:gem:2","qty":3,"name":"Peridot"},{"id":"item:aether_legacy:skyroot_stick","qty":2,"name":"Skyroot Stick"}]}],"item:projectred-exploration:iron_sickle":[{"id":61549,"c":"minecraft.crafting","cn":"Crafting","ip":"data/locales/en_us/categories/minecraft.crafting/recipe_9180.png","o":[{"id":"item:projectred-exploration:iron_sickle","name":"Iron Sickle"}],"in":[{"id":"item:minecraft:iron_ingot","qty":3,"name":"Iron Ingot"},{"id":"item:natura:sticks:1","qty":1,"name":"Silverbell Sticks"}]}],"item:projectred-exploration:golden_sickle":[{"id":61550,"c":"minecraft.crafting","cn":"Crafting","ip":"data/locales/en_us/categories/minecraft.crafting/recipe_9181.png","o":[{"id":"item:projectred-exploration:golden_sickle","name":"Golden Sickle"}],"in":[{"id":"item:minecraft:gold_ingot","qty":3,"name":"Gold Ingot"},{"id":"item:natura:sticks:9","qty":1,"name":"Ghostwood Sticks"}]}],"item:projectred-exploration:golden_saw":[{"id":61551,"c":"minecraft.crafting","cn":"Crafting","ip":"data/locales/en_us/categories/minecraft.crafting/recipe_9182.png","o":[{"id":"item:projectred-exploration:golden_saw","name":"Golden Saw"}],"in":[{"id":"item:natura:sticks:4","qty":2,"name":"Willow Sticks"},{"id":"item:tconstruct:stone_stick","qty":2,"name":"Stone Rod"},{"id":"item:minecraft:gold_ingot","qty":2,"name":"Gold Ingot"}]}],"item:projectred-exploration:diamond_sickle":[{"id":61552,"c":"minecraft.crafting","cn":"Crafting","ip":"data/locales/en_us/categories/minecraft.crafting/recipe_9183.png","o":[{"id":"item:projectred-exploration:diamond_sickle","name":"Diamond Sickle"}],"in":[{"id":"item:minecraft:diamond","qty":3,"name":"Diamond"},{"id":"item:biomesoplenty:bamboo:0","qty":1,"name":"Bamboo"}]}],"item:projectred-exploration:athame":[{"id":61553,"c":"minecraft.crafting","cn":"Crafting","ip":"data/locales/en_us/categories/minecraft.crafting/recipe_9184.png","o":[{"id":"item:projectred-exploration:athame","name":"Athame"}],"in":[{"id":"item:thermalfoundation:material:130","qty":1,"name":"Silver Ingot"},{"id":"item:natura:sticks:7","qty":1,"name":"Sakura Sticks"}]}],"item:projectred-exploration:backpack:4":[{"id":61555,"c":"minecraft.crafting","cn":"Crafting","ip":"data/locales/en_us/categories/minecraft.crafting/recipe_9186.png","o":[{"id":"item:projectred-exploration:backpack:4","name":"Yellow Backpack"}],"in":[{"id":"item:projectred-exploration:backpack:8","qty":1,"name":"Light Grey Backpack"},{"id":"item:thermalfoundation:dye:11","qty":1,"name":"Yellow Pigment"}]},{"id":61556,"c":"minecraft.crafting","cn":"Crafting","ip":"data/locales/en_us/categories/minecraft.crafting/recipe_9187.png","o":[{"id":"item:projectred-exploration:backpack:4","name":"Yellow Backpack"}],"in":[{"id":"item:projectred-core:resource_item:420","qty":8,"name":"Woven Cloth"},{"id":"item:gendustry:honey_drop:21","qty":1,"name":"Yellow Colored Honey Drop"}]}],"item:projectred-exploration:backpack:0":[{"id":61557,"c":"minecraft.crafting","cn":"Crafting","ip":"data/locales/en_us/categories/minecraft.crafting/recipe_9188.png","o":[{"id":"item:projectred-exploration:backpack:0","name":"White Backpack"}],"in":[{"id":"item:projectred-exploration:backpack:7","qty":1,"name":"Grey Backpack"},{"id":"item:gendustry:honey_drop:25","qty":1,"name":"White Colored Honey Drop"}]},{"id":61558,"c":"minecraft.crafting","cn":"Crafting","ip":"data/locales/en_us/categories/minecraft.crafting/recipe_9189.png","o":[{"id":"item:projectred-exploration:backpack:0","name":"White Backpack"}],"in":[{"id":"item:projectred-core:resource_item:420","qty":8,"name":"Woven Cloth"}]}],"item:projectred-exploration:backpack:14":[{"id":61559,"c":"minecraft.crafting","cn":"Crafting","ip":"data/locales/en_us/categories/minecraft.crafting/recipe_9190.png","o":[{"id":"item:projectred-exploration:backpack:14","name":"Red Backpack"}],"in":[{"id":"item:projectred-exploration:backpack:1","qty":1,"name":"Orange Backpack"},{"id":"item:thermalfoundation:dye:1","qty":1,"name":"Red Pigment"}]},{"id":61560,"c":"minecraft.crafting","cn":"Crafting","ip":"data/locales/en_us/categories/minecraft.crafting/recipe_9191.png","o":[{"id":"item:projectred-exploration:backpack:14","name":"Red Backpack"}],"in":[{"id":"item:projectred-core:resource_item:420","qty":8,"name":"Woven Cloth"},{"id":"item:thermalfoundation:dye:1","qty":1,"name":"Red Pigment"}]}],"item:projectred-exploration:backpack:10":[{"id":61561,"c":"minecraft.crafting","cn":"Crafting","ip":"data/locales/en_us/categories/minecraft.crafting/recipe_9192.png","o":[{"id":"item:projectred-exploration:backpack:10","name":"Purple Backpack"}],"in":[{"id":"item:projectred-exploration:backpack:3","qty":1,"name":"Light Blue Backpack"},{"id":"item:gendustry:honey_drop:15","qty":1,"name":"Purple Colored Honey Drop"}]},{"id":61562,"c":"minecraft.crafting","cn":"Crafting","ip":"data/locales/en_us/categories/minecraft.crafting/recipe_9193.png","o":[{"id":"item:projectred-exploration:backpack:10","name":"Purple Backpack"}],"in":[{"id":"item:projectred-core:resource_item:420","qty":8,"name":"Woven Cloth"},{"id":"item:erebus:giant_flower:4","qty":1,"name":"Purple Petal Block"}]}],"item:projectred-exploration:backpack:6":[{"id":61563,"c":"minecraft.crafting","cn":"Crafting","ip":"data/locales/en_us/categories/minecraft.crafting/recipe_9194.png","o":[{"id":"item:projectred-exploration:backpack:6","name":"Pink Backpack"}],"in":[{"id":"item:projectred-exploration:backpack:13","qty":1,"name":"Green Backpack"},{"id":"item:gendustry:honey_drop:19","qty":1,"name":"Pink Colored Honey Drop"}]},{"id":61564,"c":"minecraft.crafting","cn":"Crafting","ip":"data/locales/en_us/categories/minecraft.crafting/recipe_9195.png","o":[{"id":"item:projectred-exploration:backpack:6","name":"Pink Backpack"}],"in":[{"id":"item:projectred-core:resource_item:420","qty":8,"name":"Woven Cloth"},{"id":"item:botania:dye:6","qty":1,"name":"Floral Pink Powder"}]}],"item:projectred-exploration:backpack:1":[{"id":61565,"c":"minecraft.crafting","cn":"Crafting","ip":"data/locales/en_us/categories/minecraft.crafting/recipe_9196.png","o":[{"id":"item:projectred-exploration:backpack:1","name":"Orange Backpack"}],"in":[{"id":"item:projectred-exploration:backpack:3","qty":1,"name":"Light Blue Backpack"},{"id":"item:gendustry:honey_drop:24","qty":1,"name":"Orange Colored Honey Drop"}]},{"id":61566,"c":"minecraft.crafting","cn":"Crafting","ip":"data/locales/en_us/categories/minecraft.crafting/recipe_9197.png","o":[{"id":"item:projectred-exploration:backpack:1","name":"Orange Backpack"}],"in":[{"id":"item:projectred-core:resource_item:420","qty":8,"name":"Woven Cloth"},{"id":"item:erebus:giant_flower:12","qty":1,"name":"Orange Petal Block"}]}],"item:projectred-exploration:backpack:2":[{"id":61567,"c":"minecraft.crafting","cn":"Crafting","ip":"data/locales/en_us/categories/minecraft.crafting/recipe_9198.png","o":[{"id":"item:projectred-exploration:backpack:2","name":"Magenta Backpack"}],"in":[{"id":"item:projectred-exploration:backpack:0","qty":1,"name":"White Backpack"},{"id":"item:extrautils2:ingredients:3","qty":1,"name":"Lunar Reactive Dust"}]},{"id":61568,"c":"minecraft.crafting","cn":"Crafting","ip":"data/locales/en_us/categories/minecraft.crafting/recipe_9199.png","o":[{"id":"item:projectred-exploration:backpack:2","name":"Magenta Backpack"}],"in":[{"id":"item:projectred-core:resource_item:420","qty":8,"name":"Woven Cloth"},{"id":"item:thermalfoundation:dye:13","qty":1,"name":"Magenta Pigment"}]}],"item:projectred-exploration:backpack:5":[{"id":61569,"c":"minecraft.crafting","cn":"Crafting","ip":"data/locales/en_us/categories/minecraft.crafting/recipe_9200.png","o":[{"id":"item:projectred-exploration:backpack:5","name":"Lime Backpack"}],"in":[{"id":"item:projectred-exploration:backpack:8","qty":1,"name":"Light Grey Backpack"},{"id":"item:minecraft:dye:10","qty":1,"name":"Lime Dye"}]},{"id":61570,"c":"minecraft.crafting","cn":"Crafting","ip":"data/locales/en_us/categories/minecraft.crafting/recipe_9201.png","o":[{"id":"item:projectred-exploration:backpack:5","name":"Lime Backpack"}],"in":[{"id":"item:projectred-core:resource_item:420","qty":8,"name":"Woven Cloth"},{"id":"item:minecraft:dye:10","qty":1,"name":"Lime Dye"}]}],"item:projectred-exploration:backpack:8":[{"id":61571,"c":"minecraft.crafting","cn":"Crafting","ip":"data/locales/en_us/categories/minecraft.crafting/recipe_9202.png","o":[{"id":"item:projectred-exploration:backpack:8","name":"Light Grey Backpack"}],"in":[{"id":"item:projectred-exploration:backpack:15","qty":1,"name":"Black Backpack"},{"id":"item:industrialforegoing:artificial_dye:8","qty":1,"name":"Light Gray Artificial Dye"}]},{"id":61572,"c":"minecraft.crafting","cn":"Crafting","ip":"data/locales/en_us/categories/minecraft.crafting/recipe_9203.png","o":[{"id":"item:projectred-exploration:backpack:8","name":"Light Grey Backpack"}],"in":[{"id":"item:projectred-core:resource_item:420","qty":8,"name":"Woven Cloth"},{"id":"item:botania:dye:8","qty":1,"name":"Floral Light Gray Powder"}]}],"item:projectred-exploration:backpack:3":[{"id":61573,"c":"minecraft.crafting","cn":"Crafting","ip":"data/locales/en_us/categories/minecraft.crafting/recipe_9204.png","o":[{"id":"item:projectred-exploration:backpack:3","name":"Light Blue Backpack"}],"in":[{"id":"item:projectred-exploration:backpack:10","qty":1,"name":"Purple Backpack"},{"id":"item:erebus:giant_flower:10","qty":1,"name":"Light Blue Petal Block"}]},{"id":61574,"c":"minecraft.crafting","cn":"Crafting","ip":"data/locales/en_us/categories/minecraft.crafting/recipe_9205.png","o":[{"id":"item:projectred-exploration:backpack:3","name":"Light Blue Backpack"}],"in":[{"id":"item:projectred-core:resource_item:420","qty":8,"name":"Woven Cloth"},{"id":"item:gendustry:honey_drop:22","qty":1,"name":"Light Blue Colored Honey Drop"}]}],"item:projectred-exploration:backpack:13":[{"id":61575,"c":"minecraft.crafting","cn":"Crafting","ip":"data/locales/en_us/categories/minecraft.crafting/recipe_9206.png","o":[{"id":"item:projectred-exploration:backpack:13","name":"Green Backpack"}],"in":[{"id":"item:projectred-exploration:backpack:4","qty":1,"name":"Yellow Backpack"},{"id":"item:botania:dye:13","qty":1,"name":"Floral Green Powder"}]},{"id":61576,"c":"minecraft.crafting","cn":"Crafting","ip":"data/locales/en_us/categories/minecraft.crafting/recipe_9207.png","o":[{"id":"item:projectred-exploration:backpack:13","name":"Green Backpack"}],"in":[{"id":"item:projectred-core:resource_item:420","qty":8,"name":"Woven Cloth"},{"id":"item:botania:dye:13","qty":1,"name":"Floral Green Powder"}]}],"item:projectred-exploration:backpack:7":[{"id":61577,"c":"minecraft.crafting","cn":"Crafting","ip":"data/locales/en_us/categories/minecraft.crafting/recipe_9208.png","o":[{"id":"item:projectred-exploration:backpack:7","name":"Grey Backpack"}],"in":[{"id":"item:projectred-exploration:backpack:0","qty":1,"name":"White Backpack"},{"id":"item:minecraft:dye:8","qty":1,"name":"Gray Dye"}]},{"id":61578,"c":"minecraft.crafting","cn":"Crafting","ip":"data/locales/en_us/categories/minecraft.crafting/recipe_9209.png","o":[{"id":"item:projectred-exploration:backpack:7","name":"Grey Backpack"}],"in":[{"id":"item:projectred-core:resource_item:420","qty":8,"name":"Woven Cloth"},{"id":"item:erebus:giant_flower:7","qty":1,"name":"Gray Petal Block"}]}],"item:projectred-exploration:backpack:9":[{"id":61579,"c":"minecraft.crafting","cn":"Crafting","ip":"data/locales/en_us/categories/minecraft.crafting/recipe_9210.png","o":[{"id":"item:projectred-exploration:backpack:9","name":"Cyan Backpack"}],"in":[{"id":"item:projectred-exploration:backpack:11","qty":1,"name":"Blue Backpack"},{"id":"item:gendustry:honey_drop:16","qty":1,"name":"Cyan Colored Honey Drop"}]},{"id":61580,"c":"minecraft.crafting","cn":"Crafting","ip":"data/locales/en_us/categories/minecraft.crafting/recipe_9211.png","o":[{"id":"item:projectred-exploration:backpack:9","name":"Cyan Backpack"}],"in":[{"id":"item:projectred-core:resource_item:420","qty":8,"name":"Woven Cloth"},{"id":"item:minecraft:dye:6","qty":1,"name":"Cyan Dye"}]}],"item:projectred-exploration:backpack:12":[{"id":61581,"c":"minecraft.crafting","cn":"Crafting","ip":"data/locales/en_us/categories/minecraft.crafting/recipe_9212.png","o":[{"id":"item:projectred-exploration:backpack:12","name":"Brown Backpack"}],"in":[{"id":"item:projectred-exploration:backpack:7","qty":1,"name":"Grey Backpack"},{"id":"item:biomesoplenty:brown_dye","qty":1,"name":"Brown Dye"}]},{"id":61582,"c":"minecraft.crafting","cn":"Crafting","ip":"data/locales/en_us/categories/minecraft.crafting/recipe_9213.png","o":[{"id":"item:projectred-exploration:backpack:12","name":"Brown Backpack"}],"in":[{"id":"item:projectred-core:resource_item:420","qty":8,"name":"Woven Cloth"},{"id":"item:nuclearcraft:cocoa_solids","qty":1,"name":"Cocoa Solids"}]}],"item:projectred-exploration:backpack:11":[{"id":61583,"c":"minecraft.crafting","cn":"Crafting","ip":"data/locales/en_us/categories/minecraft.crafting/recipe_9214.png","o":[{"id":"item:projectred-exploration:backpack:11","name":"Blue Backpack"}],"in":[{"id":"item:projectred-exploration:backpack:1","qty":1,"name":"Orange Backpack"},{"id":"item:minecraft:dye:4","qty":1,"name":"Lapis Lazuli"}]},{"id":61584,"c":"minecraft.crafting","cn":"Crafting","ip":"data/locales/en_us/categories/minecraft.crafting/recipe_9215.png","o":[{"id":"item:projectred-exploration:backpack:11","name":"Blue Backpack"}],"in":[{"id":"item:projectred-core:resource_item:420","qty":8,"name":"Woven Cloth"},{"id":"item:biomesoplenty:blue_dye","qty":1,"name":"Blue Dye"}]}],"item:projectred-exploration:backpack:15":[{"id":61585,"c":"minecraft.crafting","cn":"Crafting","ip":"data/locales/en_us/categories/minecraft.crafting/recipe_9216.png","o":[{"id":"item:projectred-exploration:backpack:15","name":"Black Backpack"}],"in":[{"id":"item:projectred-exploration:backpack:9","qty":1,"name":"Cyan Backpack"},{"id":"item:gendustry:honey_drop:10","qty":1,"name":"Black Colored Honey Drop"}]},{"id":61586,"c":"minecraft.crafting","cn":"Crafting","ip":"data/locales/en_us/categories/minecraft.crafting/recipe_9217.png","o":[{"id":"item:projectred-exploration:backpack:15","name":"Black Backpack"}],"in":[{"id":"item:projectred-core:resource_item:420","qty":8,"name":"Woven Cloth"},{"id":"item:enderio:item_material:50","qty":1,"name":"Organic Black Dye"}]}],"item:projectred-exploration:stone_wall:9":[{"id":61587,"c":"minecraft.crafting","cn":"Crafting","ip":"data/locales/en_us/categories/minecraft.crafting/recipe_9218.png","o":[{"id":"item:projectred-exploration:stone_wall:9","qty":6,"name":"Tin Wall"}],"in":[{"id":"item:chisel:blocktin:6","qty":6,"name":"Block of Tin"}]}],"item:projectred-exploration:stone_wall:10":[{"id":61588,"c":"minecraft.crafting","cn":"Crafting","ip":"data/locales/en_us/categories/minecraft.crafting/recipe_9219.png","o":[{"id":"item:projectred-exploration:stone_wall:10","qty":6,"name":"Silver Wall"}],"in":[{"id":"item:nuclearcraft:ingot_block:13","qty":6,"name":"Silver Block"}]}],"item:projectred-exploration:stone_wall:6":[{"id":61589,"c":"minecraft.crafting","cn":"Crafting","ip":"data/locales/en_us/categories/minecraft.crafting/recipe_9220.png","o":[{"id":"item:projectred-exploration:stone_wall:6","qty":6,"name":"Sapphire Wall"}],"in":[{"id":"item:projectred-exploration:stone:6","qty":6,"name":"Block of Sapphire"}]}],"item:projectred-exploration:stone_wall:5":[{"id":61590,"c":"minecraft.crafting","cn":"Crafting","ip":"data/locales/en_us/categories/minecraft.crafting/recipe_9221.png","o":[{"id":"item:projectred-exploration:stone_wall:5","qty":6,"name":"Ruby Wall"}],"in":[{"id":"item:techreborn:storage2:3","qty":6,"name":"Block of Reborn Ruby"}]}],"item:projectred-exploration:stone_wall:7":[{"id":61591,"c":"minecraft.crafting","cn":"Crafting","ip":"data/locales/en_us/categories/minecraft.crafting/recipe_9222.png","o":[{"id":"item:projectred-exploration:stone_wall:7","qty":6,"name":"Peridot Wall"}],"in":[{"id":"item:projectred-exploration:stone:7","qty":6,"name":"Block of Peridot"}]}],"item:projectred-exploration:stone_wall:0":[{"id":61592,"c":"minecraft.crafting","cn":"Crafting","ip":"data/locales/en_us/categories/minecraft.crafting/recipe_9223.png","o":[{"id":"item:projectred-exploration:stone_wall:0","qty":6,"name":"Marble Wall"}],"in":[{"id":"item:chisel:marblepillar:4","qty":6,"name":"Marble Pillar"}]}],"item:projectred-exploration:stone_wall:1":[{"id":61593,"c":"minecraft.crafting","cn":"Crafting","ip":"data/locales/en_us/categories/minecraft.crafting/recipe_9224.png","o":[{"id":"item:projectred-exploration:stone_wall:1","qty":6,"name":"Marble Brick Wall"}],"in":[{"id":"item:projectred-exploration:stone:1","qty":6,"name":"Marble Brick"}]}],"item:projectred-exploration:stone_wall:11":[{"id":61594,"c":"minecraft.crafting","cn":"Crafting","ip":"data/locales/en_us/categories/minecraft.crafting/recipe_9225.png","o":[{"id":"item:projectred-exploration:stone_wall:11","qty":6,"name":"Electrotine Wall"}],"in":[{"id":"item:projectred-exploration:stone:11","qty":6,"name":"Block of Electrotine"}]}],"item:projectred-exploration:stone_wall:8":[{"id":61595,"c":"minecraft.crafting","cn":"Crafting","ip":"data/locales/en_us/categories/minecraft.crafting/recipe_9226.png","o":[{"id":"item:projectred-exploration:stone_wall:8","qty":6,"name":"Copper Wall"}],"in":[{"id":"item:chisel:blockcopper:1","qty":6,"name":"Block of Copper"}]}],"item:projectred-exploration:stone_wall:3":[{"id":61596,"c":"minecraft.crafting","cn":"Crafting","ip":"data/locales/en_us/categories/minecraft.crafting/recipe_9227.png","o":[{"id":"item:projectred-exploration:stone_wall:3","qty":6,"name":"Basalt Wall"}],"in":[{"id":"item:chisel:basalt:2","qty":6,"name":"Basalt"}]}],"item:projectred-exploration:stone_wall:2":[{"id":61597,"c":"minecraft.crafting","cn":"Crafting","ip":"data/locales/en_us/categories/minecraft.crafting/recipe_9228.png","o":[{"id":"item:projectred-exploration:stone_wall:2","qty":6,"name":"Basalt Cobblestone Wall"}],"in":[{"id":"item:projectred-exploration:stone:2","qty":6,"name":"Basalt Cobblestone"}]}],"item:projectred-exploration:stone_wall:4":[{"id":61598,"c":"minecraft.crafting","cn":"Crafting","ip":"data/locales/en_us/categories/minecraft.crafting/recipe_9229.png","o":[{"id":"item:projectred-exploration:stone_wall:4","qty":6,"name":"Basalt Brick Wall"}],"in":[{"id":"item:projectred-exploration:stone:4","qty":6,"name":"Basalt Brick"}]}],"item:projectred-exploration:stone:6":[{"id":61600,"c":"minecraft.crafting","cn":"Crafting","ip":"data/locales/en_us/categories/minecraft.crafting/recipe_9231.png","o":[{"id":"item:projectred-exploration:stone:6","name":"Block of Sapphire"}],"in":[{"id":"item:iceandfire:sapphire_gem","qty":9,"name":"Singing Sapphire"}]}],"item:projectred-exploration:stone:5":[{"id":61602,"c":"minecraft.crafting","cn":"Crafting","ip":"data/locales/en_us/categories/minecraft.crafting/recipe_9233.png","o":[{"id":"item:projectred-exploration:stone:5","name":"Block of Ruby"}],"in":[{"id":"item:projectred-core:resource_item:200","qty":9,"name":"Ruby"}]}],"item:projectred-exploration:stone:7":[{"id":61604,"c":"minecraft.crafting","cn":"Crafting","ip":"data/locales/en_us/categories/minecraft.crafting/recipe_9235.png","o":[{"id":"item:projectred-exploration:stone:7","name":"Block of Peridot"}],"in":[{"id":"item:techreborn:gem:2","qty":9,"name":"Reborn Peridot"}]}],"item:projectred-exploration:stone:11":[{"id":61606,"c":"minecraft.crafting","cn":"Crafting","ip":"data/locales/en_us/categories/minecraft.crafting/recipe_9237.png","o":[{"id":"item:projectred-exploration:stone:11","name":"Block of Electrotine"}],"in":[{"id":"item:projectred-core:resource_item:105","qty":9,"name":"Electrotine"}]}],"item:projectred-exploration:stone:4":[{"id":61608,"c":"minecraft.crafting","cn":"Crafting","ip":"data/locales/en_us/categories/minecraft.crafting/recipe_9239.png","o":[{"id":"item:projectred-exploration:stone:4","qty":4,"name":"Basalt Brick"}],"in":[{"id":"item:projectred-exploration:stone:3","qty":4,"name":"Basalt"}]}],"item:projectred-exploration:barrel:0":[{"id":61609,"c":"minecraft.crafting","cn":"Crafting","ip":"data/locales/en_us/categories/minecraft.crafting/recipe_9240.png","o":[{"id":"item:projectred-exploration:barrel:0","name":"Item Barrel"}],"in":[{"id":"item:forestry:logs.0:1","qty":5,"name":"Teak Wood"},{"id":"item:forestry:slabs.0:1","qty":1,"name":"Teak Wood Slab"},{"id":"item:minecraft:iron_ingot","qty":2,"name":"Iron Ingot"}]}]}